petracore_django/__init__.py
petracore_django/cli.py
petracore_django/scaffold.py
petracore_django/messaging/__init__.py
petracore_django/messaging/base.py
petracore_django/messaging/tasks.py
petracore_django/messaging/channels/__init__.py
petracore_django/messaging/channels/base.py
petracore_django/messaging/channels/push.py
petracore_django/messaging/channels/sms.py
petracore_django/messaging/channels/email/postmark.py
petracore_django/messaging/channels/email/resend.py
petracore_django/templates/core_base_service.py.tmpl
petracore_django/templates/core_custom_authentication.py.tmpl
petracore_django/templates/core_exceptions.py.tmpl
petracore_django/templates/core_models.py.tmpl
petracore_django/templates/core_serializers.py.tmpl
petracore_django/templates/core_urls.py.tmpl
petracore_django/templates/core_utils.py.tmpl
petracore_django/templates/project_readme.md.tmpl
petracore_django/templates/startapp_plus.py.tmpl
petracore_django/templates/user_models.py.tmpl
petracore_django/templates/user_serializers.py.tmpl
petracore_django/templates/user_services.py.tmpl
petracore_django/templates/user_urls.py.tmpl
petracore_django/templates/user_views.py.tmpl
petracore_django_backend_starter-0.1.1.dist-info/licenses/LICENSE
petracore_django_backend_starter-0.1.1.dist-info/METADATA
petracore_django_backend_starter-0.1.1.dist-info/WHEEL
petracore_django_backend_starter-0.1.1.dist-info/entry_points.txt
petracore_django_backend_starter-0.1.1.dist-info/top_level.txt
petracore_django_backend_starter-0.1.1.dist-info/RECORD
