Metadata-Version: 2.4
Name: petracore-django-backend-starter
Version: 0.1.1
Summary: PetraCore 's Django project/app scaffolder with services layer and messaging functionalities
Author: Maro Okegbero
License: ---
Keywords: django,scaffold,rest-framework,starter
Classifier: Development Status :: 3 - Alpha
Classifier: Programming Language :: Python
Classifier: Programming Language :: Python :: 3
Classifier: Programming Language :: Python :: 3 :: Only
Classifier: Programming Language :: Python :: 3.10
Classifier: Programming Language :: Python :: 3.11
Classifier: Programming Language :: Python :: 3.12
Classifier: Framework :: Django
Classifier: License :: OSI Approved :: MIT License
Classifier: Operating System :: OS Independent
Requires-Python: >=3.10
License-File: LICENSE
Requires-Dist: Django>=4.2
Requires-Dist: djangorestframework>=3.15
Requires-Dist: PyJWT<3,>=2.8
Requires-Dist: requests<3,>=2.32
Dynamic: license-file
